luminesce/__init__.py
luminesce/api/__init__.py
luminesce/api/application_metadata_api.py
luminesce/api/binary_downloading_api.py
luminesce/api/certificate_management_api.py
luminesce/api/current_table_field_catalog_api.py
luminesce/api/health_checking_endpoint_api.py
luminesce/api/historically_executed_queries_api.py
luminesce/api/multi_query_execution_api.py
luminesce/api/sql_background_execution_api.py
luminesce/api/sql_design_api.py
luminesce/api/sql_execution_api.py
luminesce/api_client.py
luminesce/api_response.py
luminesce/configuration.py
luminesce/exceptions.py
luminesce/extensions/__init__.py
luminesce/extensions/api_client.py
luminesce/extensions/api_client_factory.py
luminesce/extensions/api_configuration.py
luminesce/extensions/configuration_loaders.py
luminesce/extensions/configuration_options.py
luminesce/extensions/file_access_token.py
luminesce/extensions/proxy_config.py
luminesce/extensions/refreshing_token.py
luminesce/extensions/rest.py
luminesce/extensions/retry.py
luminesce/extensions/socket_keep_alive.py
luminesce/extensions/tcp_keep_alive_connector.py
luminesce/models/__init__.py
luminesce/models/access_controlled_action.py
luminesce/models/access_controlled_resource.py
luminesce/models/access_controlled_resource_identifier_part_schema_attribute.py
luminesce/models/action_id.py
luminesce/models/aggregate_function.py
luminesce/models/aggregation.py
luminesce/models/auto_detect_type.py
luminesce/models/available_field.py
luminesce/models/available_parameter.py
luminesce/models/background_multi_query_progress_response.py
luminesce/models/background_multi_query_response.py
luminesce/models/background_query_cancel_response.py
luminesce/models/background_query_progress_response.py
luminesce/models/background_query_response.py
luminesce/models/background_query_state.py
luminesce/models/case_statement_design.py
luminesce/models/case_statement_item.py
luminesce/models/certificate_action.py
luminesce/models/certificate_file_type.py
luminesce_sdk-2.4.10.dist-info/METADATA
luminesce_sdk-2.4.10.dist-info/WHEEL
luminesce_sdk-2.4.10.dist-info/RECORD
